AlgumTesteCoisa/AlgumTesteCoisa.py
AlgumTesteCoisa/__init__.py
AlgumTesteCoisa-0.2.dist-info/LICENSE
AlgumTesteCoisa-0.2.dist-info/METADATA
AlgumTesteCoisa-0.2.dist-info/WHEEL
AlgumTesteCoisa-0.2.dist-info/top_level.txt
AlgumTesteCoisa-0.2.dist-info/RECORD
