Metadata-Version: 2.1
Name: AlgumTesteCoisa
Version: 0.2
Summary: Função para dar um oi.
Author: VictorSalg
Author-email: victorfsalgueiros@gmail.com
License-File: LICENSE
